src/pc.v
module pc (
    input clk,
    input reset,
    output reg [4:0] pc_out
);

    always @(posedge clk or posedge reset) begin
        if (reset)
            pc_out <= 0;
        else
            pc_out <= pc_out + 1;
    end

endmodule

testbench/pc_tb.v
module pc_tb;

    reg clk, reset;
    wire [4:0] pc_out;

    pc uut (
        .clk(clk),
        .reset(reset),
        .pc_out(pc_out)
    );

    initial begin
        $dumpfile("pc.vcd");
        $dumpvars(0, pc_tb);

        clk = 0; reset = 1; #10;
        reset = 0;

        #100;
        $finish;
    end

    always #5 clk = ~clk;

endmodule

simulation files/pc.vcd
$date
	Sat Aug 16 13:56:01 2025
$end
$version
	Icarus Verilog
$end
$timescale
	1s
$end
$scope module pc_tb $end
$var wire 5 ! pc_out [4:0] $end
$var reg 1 " clk $end
$var reg 1 # reset $end
$scope module uut $end
$var wire 1 " clk $end
$var wire 1 # reset $end
$var reg 5 $ pc_out [4:0] $end
$upscope $end
$upscope $end
$enddefinitions $end
#0
$dumpvars
b0 $
1#
0"
b0 !
$end
#5
1"
#10
0"
0#
#15
b1 !
b1 $
1"
#20
0"
#25
b10 !
b10 $
1"
#30
0"
#35
b11 !
b11 $
1"
#40
0"
#45
b100 !
b100 $
1"
#50
0"
#55
b101 !
b101 $
1"
#60
0"
#65
b110 !
b110 $
1"
#70
0"
#75
b111 !
b111 $
1"
#80
0"
#85
b1000 !
b1000 $
1"
#90
0"
#95
b1001 !
b1001 $
1"
#100
0"
#105
b1010 !
b1010 $
1"
